multi_event_bus/__init__.py
multi_event_bus/event.py
multi_event_bus/event_bus.py
multi_event_bus/exceptions.py
multi_event_bus/multi_lock.py
multi_event_bus-0.2.0.dist-info/entry_points.txt
multi_event_bus-0.2.0.dist-info/WHEEL
multi_event_bus-0.2.0.dist-info/METADATA
multi_event_bus-0.2.0.dist-info/RECORD
