Metadata-Version: 2.1
Name: multi-event-bus
Version: 0.2.0
Summary: event bus implementation in python with sync and async support
Home-page: https://github.com/hvuhsg/event-bus
Keywords: event,bus,event-bus,event_bus,async,blocking
Author: yehoyada
Author-email: hvuhsg5@gmail.com
Requires-Python: >=3.8,<4.0
Classifier: Development Status :: 3 - Alpha
Classifier: Intended Audience :: Developers
Classifier: Operating System :: OS Independent
Classifier: Programming Language :: Python :: 3
Classifier: Programming Language :: Python :: 3.10
Classifier: Programming Language :: Python :: 3.11
Classifier: Programming Language :: Python :: 3.8
Classifier: Programming Language :: Python :: 3.9
Classifier: Topic :: Software Development :: Libraries
Classifier: Topic :: Software Development :: Libraries :: Python Modules
Requires-Dist: aioredis[hiredis] (>=2.0.1,<3.0.0)
Requires-Dist: jsonschema
Requires-Dist: redis (>=4.2.2,<5.0.0)
Requires-Dist: types-redis (>=4.1.19,<5.0.0)
Project-URL: Repository, https://github.com/hvuhsg/event-bus
